{
    "bsonType": "object",
    "switch": {
      "branches": [
        {
          "case": { "$eq": ["$$this.name", "VERSION"] },
          "then": {
            "required": ["name", "description", "version"],
            "properties": {
              "name": { 
                "description":"VERSION is the key that identifies this document as a Scheam Version document",
                "bsonType": "string", 
                "maxLength": 32 },
              "description": { 
                "description":"Schema Version is the description on ",
                "bsonType": "string", 
                "maxLength": 256 },
              "version": { 
                "description":"",
                "bsonType": "string", 
                "maxLength": 20 }
            }
          }
        },
        {
          "case": { "$ne": ["$$this.name", "VERSION"] },
          "then": {
            "required": ["name", "status"],
            "properties": {
                "name": { 
                    "description": "The Partner name",
                    "bsonType": "string", 
                    "maxLength": 32
                },
                "status": { 
                    "description": "The status of this partnership",
                    "bsonType": "string",
                    "enum": ["Lead", "Pending", "Active", "Archived"]
                },
                "description": { 
                    "description": "Notes or other descriptions of the partner",
                    "bsonType": "string", 
                    "maxLength": 256 
                },
                "url": {
                    "description": "Partner Company website",
                    "bsonType": "string",
                    "maxLength": 256,
                    "pattern": "^(https?|ftp)://[^\\s/$.?#].[^\\s]*$"
              }
            }
          }
        }
      ]
    }
  }
  